codecov_cli/__init__.py
codecov_cli/branding.py
codecov_cli/fallbacks.py
codecov_cli/main.py
codecov_cli/opentelemetry.py
codecov_cli/types.py
codecov_cli/commands/__init__.py
codecov_cli/commands/base_picking.py
codecov_cli/commands/commit.py
codecov_cli/commands/create_report_result.py
codecov_cli/commands/empty_upload.py
codecov_cli/commands/get_report_results.py
codecov_cli/commands/labelanalysis.py
codecov_cli/commands/process_test_results.py
codecov_cli/commands/report.py
codecov_cli/commands/send_notifications.py
codecov_cli/commands/staticanalysis.py
codecov_cli/commands/upload.py
codecov_cli/commands/upload_coverage.py
codecov_cli/commands/upload_process.py
codecov_cli/helpers/__init__.py
codecov_cli/helpers/args.py
codecov_cli/helpers/config.py
codecov_cli/helpers/encoder.py
codecov_cli/helpers/folder_searcher.py
codecov_cli/helpers/git.py
codecov_cli/helpers/glob.py
codecov_cli/helpers/logging_utils.py
codecov_cli/helpers/options.py
codecov_cli/helpers/request.py
codecov_cli/helpers/upload_type.py
codecov_cli/helpers/validators.py
codecov_cli/helpers/versioning_systems.py
codecov_cli/helpers/ci_adapters/__init__.py
codecov_cli/helpers/ci_adapters/appveyor_ci.py
codecov_cli/helpers/ci_adapters/azure_pipelines.py
codecov_cli/helpers/ci_adapters/base.py
codecov_cli/helpers/ci_adapters/bitbucket_ci.py
codecov_cli/helpers/ci_adapters/bitrise_ci.py
codecov_cli/helpers/ci_adapters/buildkite.py
codecov_cli/helpers/ci_adapters/circleci.py
codecov_cli/helpers/ci_adapters/cirrus_ci.py
codecov_cli/helpers/ci_adapters/cloudbuild.py
codecov_cli/helpers/ci_adapters/codebuild.py
codecov_cli/helpers/ci_adapters/droneci.py
codecov_cli/helpers/ci_adapters/github_actions.py
codecov_cli/helpers/ci_adapters/gitlab_ci.py
codecov_cli/helpers/ci_adapters/heroku.py
codecov_cli/helpers/ci_adapters/jenkins.py
codecov_cli/helpers/ci_adapters/local.py
codecov_cli/helpers/ci_adapters/teamcity.py
codecov_cli/helpers/ci_adapters/travis_ci.py
codecov_cli-11.2.6.dist-info/licenses/LICENSE
codecov_cli-11.2.6.dist-info/METADATA
codecov_cli-11.2.6.dist-info/WHEEL
codecov_cli-11.2.6.dist-info/entry_points.txt
codecov_cli-11.2.6.dist-info/top_level.txt
codecov_cli-11.2.6.dist-info/RECORD
