Metadata-Version: 2.4
Name: codecov-cli
Version: 11.2.6
Summary: Codecov Command Line Interface
Author-email: Tom Hu <thomas.hu@sentry.io>
Maintainer-email: Codecov Support <support@codecov.io>
Project-URL: Homepage, https://about.codecov.io
Project-URL: CI: GitHub, https://github.com/getsentry/prevent-cli/actions/workflows/ci.yml
Project-URL: Docs, https://docs.codecov.com
Project-URL: GitHub: issues, https://github.com/getsentry/prevent-cli/issues
Project-URL: GitHub: repo, https://github.com/getsentry/prevent-cli
Requires-Python: >=3.9
License-File: LICENSE
Requires-Dist: click<8.3.0,>=8.0.0
Requires-Dist: ijson==3.*
Requires-Dist: PyYAML==6.*
Requires-Dist: responses==0.21.*
Requires-Dist: sentry-sdk==2.*
Requires-Dist: test-results-parser==0.6.1
Dynamic: license-file
